temporalmemai/__init__.py
temporalmemai/memory.py
temporalmemai/models.py
temporalmemai/embedding/__init__.py
temporalmemai/embedding/openai_embedder.py
temporalmemai/llm/__init__.py
temporalmemai/llm/extractor.py
temporalmemai/prompts/fact_extraction_prompt.py
temporalmemai/rerankers/base.py
temporalmemai/rerankers/cohere_reranker.py
temporalmemai/rerankers/factory.py
temporalmemai/rerankers/huggingface_reranker.py
temporalmemai/rerankers/llm_reranker.py
temporalmemai/storage/__init__.py
temporalmemai/storage/qdrant_store.py
temporalmemai/storage/sqlite_store.py
temporalmemai/temporal/__init__.py
temporalmemai/temporal/engine.py
temporalmemai-0.1.0.dist-info/METADATA
temporalmemai-0.1.0.dist-info/WHEEL
temporalmemai-0.1.0.dist-info/licenses/LICENSE
temporalmemai-0.1.0.dist-info/RECORD
