Metadata-Version: 2.4
Name: temporalmemai
Version: 0.1.0
Summary: A temporal-aware AI memory engine that extracts, stores, and retrieves long-term user memories with built-in decay, versioning, and freshness scoring
Project-URL: Homepage, https://github.com/29m10/temporalmemai
Project-URL: Repository, https://github.com/29m10/temporalmemai
Project-URL: Documentation, https://github.com/29m10/temporalmemai#readme
Project-URL: Issues, https://github.com/29m10/temporalmemai/issues
Author: TemporalMemAI Contributors
License: Apache-2.0
License-File: LICENSE
Keywords: ai,embeddings,llm,memory,qdrant,reranking,semantic-search,temporal,vector-search
Classifier: Development Status :: 4 - Beta
Classifier: Intended Audience :: Developers
Classifier: License :: OSI Approved :: Apache Software License
Classifier: Operating System :: OS Independent
Classifier: Programming Language :: Python :: 3
Classifier: Programming Language :: Python :: 3.13
Classifier: Topic :: Scientific/Engineering :: Artificial Intelligence
Classifier: Topic :: Software Development :: Libraries :: Python Modules
Requires-Python: >=3.13
Requires-Dist: openai>=1.0.0
Requires-Dist: pydantic>=2.0.0
Requires-Dist: python-dotenv>=1.0.0
Requires-Dist: qdrant-client>=1.7.0
Provides-Extra: all
Requires-Dist: cohere>=4.0.0; extra == 'all'
Requires-Dist: numpy>=1.24.0; extra == 'all'
Requires-Dist: torch>=2.0.0; extra == 'all'
Requires-Dist: transformers>=4.30.0; extra == 'all'
Provides-Extra: cohere
Requires-Dist: cohere>=4.0.0; extra == 'cohere'
Provides-Extra: huggingface
Requires-Dist: numpy>=1.24.0; extra == 'huggingface'
Requires-Dist: torch>=2.0.0; extra == 'huggingface'
Requires-Dist: transformers>=4.30.0; extra == 'huggingface'
